AGONS/AGONSModule.py
AGONS/__init__.py
AGONS/test.py
AGONS-1.1.6.dist-info/METADATA
AGONS-1.1.6.dist-info/WHEEL
AGONS-1.1.6.dist-info/top_level.txt
AGONS-1.1.6.dist-info/RECORD
