Metadata-Version: 2.1
Name: AGONS
Version: 1.1.6
Summary: Package to use Yigit Lab developed AGONS algorithm for the machine learning powered nanosensor array (MILAN). This package has high potential to be useful towards other nanosensor arrays as well.
Home-page: https://github.com/CWSmith022/yigit-lab
Download-URL: https://github.com/user/reponame/archive/v_01.tar.gz
Author: Christopher Smith
Author-email: c.w.smith022@gmail.com
License: MIT
Keywords: nanosensors,fluorescence,automation,feature selection
Platform: UNKNOWN
Classifier: Development Status :: 3 - Alpha
Classifier: Intended Audience :: Developers
Classifier: Topic :: Software Development :: Build Tools
Classifier: License :: OSI Approved :: MIT License
Classifier: Programming Language :: Python :: 3.4
Classifier: Programming Language :: Python :: 3.7
Classifier: Programming Language :: Python :: 3.8
Classifier: Programming Language :: Python :: 3.9
Requires-Dist: IPython
Requires-Dist: matplotlib
Requires-Dist: ipympl
Requires-Dist: seaborn
Requires-Dist: sklearn
Requires-Dist: numpy
Requires-Dist: pandas
Requires-Dist: time
